{
  "game": "lp85",
  "levels": {
    "1": {
      "actions_count": 446,
      "deterministic": true,
      "search_steps": 6446,
      "kb_actions": 216,
      "click_actions": 230,
      "action_composition": {
        "CLICK": 230,
        "ACTION4": 41,
        "ACTION1": 24,
        "ACTION5": 33,
        "ACTION3": 30,
        "ACTION2": 34,
        "ACTION7": 29,
        "ACTION6": 25
      },
      "trimmed_sequence": [
        1631,
        852,
        3,
        1126,
        0,
        602,
        2142,
        2529,
        0,
        0,
        3816,
        1592,
        4,
        2,
        2327,
        1249,
        486,
        1198,
        2498,
        3611,
        4080,
        1850,
        1879,
        2947,
        1051,
        3355,
        4,
        450,
        4,
        96,
        0,
        2315,
        1897,
        917,
        3,
        1,
        4072,
        655,
        2652,
        0,
        603,
        581,
        2507,
        2683,
        3460,
        308,
        3360,
        2,
        6,
        6
      ]
    }
  },
  "max_level_reached": 1,
  "elapsed": 135.5
}